ipulse_shared_ai_ftredge/__init__.py
ipulse_shared_ai_ftredge/models/__init__.py
ipulse_shared_ai_ftredge/models/common/__init__.py
ipulse_shared_ai_ftredge/models/common/base_versioned_model.py
ipulse_shared_ai_ftredge/models/intelligence_designs/__init__.py
ipulse_shared_ai_ftredge/models/intelligence_designs/ai_analyst.py
ipulse_shared_ai_ftredge/models/intelligence_designs/ai_analyst_mode.py
ipulse_shared_ai_ftredge/models/intelligence_designs/ai_model_specification.py
ipulse_shared_ai_ftredge/models/intelligence_designs/ai_model_version.py
ipulse_shared_ai_ftredge/models/intelligence_designs/ai_training_configuration.py
ipulse_shared_ai_ftredge/models/intelligence_designs/ai_training_run.py
ipulse_shared_ai_ftredge/models/intelligence_designs/analyst_persona.py
ipulse_shared_ai_ftredge/models/intelligence_evaluation/__init__.py
ipulse_shared_ai_ftredge/models/intelligence_evaluation/ai_model_performance_evaluation.py
ipulse_shared_ai_ftredge/models/intelligence_mlops/__init__.py
ipulse_shared_ai_ftredge/models/intelligence_mlops/ai_model_serving_instance.py
ipulse_shared_ai_ftredge/models/intelligence_outputs/__init__.py
ipulse_shared_ai_ftredge/models/intelligence_outputs/classifications/__init__.py
ipulse_shared_ai_ftredge/models/intelligence_outputs/classifications/classification_inference_base.py
ipulse_shared_ai_ftredge/models/intelligence_outputs/regressions/__init__.py
ipulse_shared_ai_ftredge/models/intelligence_outputs/regressions/regression_estimate_base.py
ipulse_shared_ai_ftredge/models/intelligence_outputs/time_series/__init__.py
ipulse_shared_ai_ftredge/models/intelligence_outputs/time_series/prediction_fincore_market_investment_thesis_with_rating.py
ipulse_shared_ai_ftredge/models/intelligence_outputs/time_series/time_series_prediction_event_base.py
ipulse_shared_ai_ftredge/models/intelligence_outputs/time_series/time_series_prediction_fincore_market.py
ipulse_shared_ai_ftredge-3.11.2.dist-info/licenses/LICENCE
ipulse_shared_ai_ftredge-3.11.2.dist-info/METADATA
ipulse_shared_ai_ftredge-3.11.2.dist-info/WHEEL
ipulse_shared_ai_ftredge-3.11.2.dist-info/top_level.txt
ipulse_shared_ai_ftredge-3.11.2.dist-info/RECORD
