Metadata-Version: 2.4
Name: ipulse_shared_ai_ftredge
Version: 3.11.2
Summary: Shared AI models for the Pulse platform project. Using AI for financial advisory and investment management.
Home-page: https://github.com/TheFutureEdge/ipulse_shared_ai
Author: russlan.ramdowar
License-File: LICENCE
Requires-Dist: ipulse_shared_base_ftredge~=12.12.0
Requires-Dist: ipulse_shared_core_ftredge~=27.9.0
Dynamic: author
Dynamic: home-page
Dynamic: license-file
Dynamic: requires-dist
Dynamic: summary
